Metadata-Version: 2.1
Name: blockmango
Version: 1.5.0
Summary: Blockman Go API package
Home-page: https://github.com/darkkpy/blockmango
Author: Dark
Author-email: darkness0777@proton.me
License: MIT
Project-URL: Documentation, https://github.com/darkkpy/blockmango/tree/main/docs
Project-URL: Source, https://github.com/darkkpy/blockmango
Project-URL: Tracker, https://github.com/darkkpy/blockmango/issues
Keywords: blockmango blockman go api wrapper
Platform: UNKNOWN
Classifier: Development Status :: 5 - Production/Stable
Classifier: Intended Audience :: Developers
Classifier: Topic :: Software Development :: Libraries :: Python Modules
Classifier: License :: OSI Approved :: MIT License
Classifier: Programming Language :: Python :: 3
Classifier: Programming Language :: Python :: 3.6
Classifier: Programming Language :: Python :: 3.7
Classifier: Programming Language :: Python :: 3.8
Classifier: Programming Language :: Python :: 3.9
Classifier: Programming Language :: Python :: 3.10
Classifier: Operating System :: OS Independent
Requires-Python: >=3.6
License-File: LICENSE.md
